{
  "output_dir": "./downloads",
  "quality": "best",
  "format": "mp4",
  "audio_format": "m4a",
  "write_subtitles": true,
  "write_thumbnail": true,
  "write_metadata": true,
  "write_description": false,
  "archive_file": "download_archive.txt",
  "enable_resume": true,
  "max_concurrent_downloads": 3,
  "download_timeout": 300,
  "max_retries": 3,
  "retry_delay": 1.0,
  "exponential_backoff": true,
  "quality_fallback_chain": [
    "best",
    "2160p",
    "1440p", 
    "1080p",
    "720p",
    "480p"
  ],
  "format_preference": [
    "mp4",
    "webm",
    "mkv"
  ],
  "profile": "desktop",
  "user_agent": null,
  "proxy": null,
  "cookies_file": null
}
